pdsx/__init__.py
pdsx/cli.py
pdsx/py.typed
pdsx/_internal/__init__.py
pdsx/_internal/auth.py
pdsx/_internal/batch.py
pdsx/_internal/config.py
pdsx/_internal/display.py
pdsx/_internal/operations.py
pdsx/_internal/output.py
pdsx/_internal/parsing.py
pdsx/_internal/resolution.py
pdsx/_internal/types.py
pdsx/_internal/web_url.py
pdsx/mcp/__init__.py
pdsx/mcp/_types.py
pdsx/mcp/client.py
pdsx/mcp/middleware.py
pdsx/mcp/server.py
pdsx-0.0.1a22.dist-info/METADATA
pdsx-0.0.1a22.dist-info/WHEEL
pdsx-0.0.1a22.dist-info/entry_points.txt
pdsx-0.0.1a22.dist-info/licenses/LICENSE
pdsx-0.0.1a22.dist-info/RECORD
