Metadata-Version: 2.4
Name: pdsx
Version: 0.0.1a22
Summary: general-purpose cli for atproto record operations
Author-email: zzstoatzz <thrast36@gmail.com>
License-Expression: MIT
License-File: LICENSE
Keywords: atproto,bluesky,cli,fastmcp,mcp,pds,records
Classifier: Development Status :: 3 - Alpha
Classifier: Intended Audience :: Developers
Classifier: License :: OSI Approved :: MIT License
Classifier: Programming Language :: Python :: 3
Classifier: Programming Language :: Python :: 3.10
Classifier: Programming Language :: Python :: 3.11
Classifier: Programming Language :: Python :: 3.12
Classifier: Programming Language :: Python :: 3.13
Classifier: Programming Language :: Python :: 3.14
Classifier: Topic :: Software Development :: Libraries :: Python Modules
Classifier: Typing :: Typed
Requires-Python: >=3.10
Requires-Dist: atproto>=0.0.63
Requires-Dist: pydantic-settings>=2.7.0
Requires-Dist: pyyaml>=6.0.3
Requires-Dist: rich>=13.0.0
Provides-Extra: mcp
Requires-Dist: fastmcp>=2.0; extra == 'mcp'
Requires-Dist: jmespath>=1.0; extra == 'mcp'
